README.md
mjs.py
setup.py
lwe_mjs.egg-info/PKG-INFO
lwe_mjs.egg-info/SOURCES.txt
lwe_mjs.egg-info/dependency_links.txt
lwe_mjs.egg-info/requires.txt
lwe_mjs.egg-info/top_level.txt