Metadata-Version: 1.1
Name: lwe-mjs
Version: 0.4.1
Summary: A JSON-Server component which uses the mapper project
Home-page: https://github.com/linuxwhatelse/mjs
Author: linuxwhatelse
Author-email: info@linuxwhatelse.com
License: GPLv3
Keywords: mapper json server mjs
Platform: UNKNOWN
Classifier: Development Status :: 4 - Beta
Classifier: Intended Audience :: Developers
Classifier: License :: OSI Approved :: GNU General Public License v3 (GPLv3)
Classifier: Operating System :: OS Independent
Classifier: Programming Language :: Python :: 3.4
Classifier: Programming Language :: Python :: 3.5
Classifier: Programming Language :: Python :: 3.6
Classifier: Topic :: Software Development :: Libraries :: Python Modules
